LICENSE
README.md
setup.py
tap_zoom/__init__.py
tap_zoom/client.py
tap_zoom/discover.py
tap_zoom/endpoints.py
tap_zoom/sync.py
tap_zoom/utils.py
tap_zoom.egg-info/PKG-INFO
tap_zoom.egg-info/SOURCES.txt
tap_zoom.egg-info/dependency_links.txt
tap_zoom.egg-info/entry_points.txt
tap_zoom.egg-info/requires.txt
tap_zoom.egg-info/top_level.txt
tap_zoom/schemas/meeting_poll_results.json
tap_zoom/schemas/meeting_polls.json
tap_zoom/schemas/meeting_questions.json
tap_zoom/schemas/meeting_registrants.json
tap_zoom/schemas/meetings.json
tap_zoom/schemas/report_meeting_participants.json
tap_zoom/schemas/report_meetings.json
tap_zoom/schemas/report_webinar_participants.json
tap_zoom/schemas/report_webinars.json
tap_zoom/schemas/users.json
tap_zoom/schemas/webinar_absentees.json
tap_zoom/schemas/webinar_panelists.json
tap_zoom/schemas/webinar_poll_results.json
tap_zoom/schemas/webinar_polls.json
tap_zoom/schemas/webinar_qna_results.json
tap_zoom/schemas/webinar_questions.json
tap_zoom/schemas/webinar_registrants.json
tap_zoom/schemas/webinar_tracking_sources.json
tap_zoom/schemas/webinars.json
tests/test_all_fields.py
tests/test_automatic_fields.py
tests/test_discovery.py
tests/test_pagination.py