Metadata-Version: 2.1
Name: tap-zoom
Version: 2.0.2
Summary: Singer.io tap for extracting data from the Zoom API
Home-page: UNKNOWN
License: UNKNOWN
Platform: UNKNOWN
Classifier: Programming Language :: Python :: 3 :: Only
License-File: LICENSE
